{
    "title_main": "1",
    "title_middle": [],
    "story": {
        "always": [
            "První věc, která tě udeří do očí, když se rozjedeš po silnici, je rychlost, se kterou se vše obrátilo v trosky. Netušil jsi, kolik práce je třeba, aby fungoval civilizovaný život. Budovy se pomalu hroutí, opuštěná auta vytvářejí na silnicích rezavějící mozaiky. Všude vyrazila tráva a&nbsp;plevel a&nbsp;není nikdo, kdo by je odstranil, a&nbsp;krajem volně pobíhají smečky psů a&nbsp;jiných divokých zvířat. Zastavíš v&nbsp;malém městě asi patnáct kilometrů od New Hope a&nbsp;vypneš motor. Náhle je mrtvé ticho přerušeno strašidelným vytím psa někde na druhém konci ulice. Rád bys vystoupil a&nbsp;prozkoumal to, ale víš, že je to zbytečné riziko. Zrovna se chystáš znovu nastartovat, když najednou do ticha práskne výstřel z&nbsp;brokovnice. Pokud chceš vystoupit z&nbsp;auta a&nbsp;zjistit, co se děje, otoč na <b>126</b>. Pokud raději z&nbsp;města odjedeš, otoč na <b>34</b>."
        ],
        "survived": [],
        "died": []
    },
    "image": "1.png",
    "options": [
        {
            "node": "126",
            "description": "Zjistit, co se děje",
            "conditions": []
        },
        {
            "node": "34",
            "description": "Odjet z města",
            "conditions": []
        }
    ],
    "show_hud": true,
    "notes": [],
    "options_luck": [],
    "options_fight_skill": [],
    "life": "nothing",
    "equipment": {
        "mode": "nothing",
        "content": []
    },
    "stats": []
}